README.rst
setup.py
django_i18n_sitemap.egg-info/PKG-INFO
django_i18n_sitemap.egg-info/SOURCES.txt
django_i18n_sitemap.egg-info/dependency_links.txt
django_i18n_sitemap.egg-info/top_level.txt
i18nsitemap/__init__.py
i18nsitemap/i18nsitemap.py