Metadata-Version: 1.1
Name: django-i18n-sitemap
Version: 0.1
Summary: Adds the possibility to have i18n urls in your sitemap
Home-page: https://github.com/TracyWebTech/django-i18n-sitemap
Author: Luan Pablo
Author-email: luan@tracy.com.br
License: GNU General Public License v2 (GPLv2)
Platform: UNKNOWN
Classifier: Development Status :: 4 - Beta
Classifier: Environment :: Web Environment
Classifier: Framework :: Django
Classifier: Intended Audience :: Developers
Classifier: License :: OSI Approved :: GNU General Public License v2 (GPLv2)
Classifier: Operating System :: OS Independent
Classifier: Programming Language :: Python
Classifier: Programming Language :: Python :: 2.6
Classifier: Programming Language :: Python :: 2.7
